{
 "title":	"AdministratorMenu App",
 "app": "AdministratorMenu",
 "vendor":"Tools",
 "version":	"1.0.0",
 "req_core_version":	"3.0",
 "license":	"GPL-2",
 "authors": [
  {
   "name": "ClicShopping",
   "company":	"ClicShopping",
   "email":	"admin@clicshopping.org",
   "website":	"https://www.clicshopping.org"
  }
 ],
 "modules": {
  "Hooks": {
   "ClicShoppingAdmin/Langues": {
    "DeleteConfirm":	"Module\\Hooks\\ClicShoppingAdmin\\Langues\\DeleteConfirm",
    "Insert":	"Module\\Hooks\\ClicShoppingAdmin\\Langues\\Insert"
   }
  }
 },
 "routes": {
  "ClicShoppingAdmin":	"Sites\\ClicShoppingAdmin\\Pages\\Home"
 }
}